{
    "os": "Linux-4.18.0-513.18.1.el8_9.x86_64-x86_64-with-glibc2.28",
    "python": "3.11.3",
    "heartbeatAt": "2025-03-04T13:22:48.273051",
    "startedAt": "2025-03-04T13:22:47.244209",
    "docker": null,
    "cuda": null,
    "args": [],
    "state": "running",
    "program": "/home/zacharyl/lab/ppg/single_run_wandb.py",
    "codePathLocal": "single_run_wandb.py",
    "codePath": "ppg/single_run_wandb.py",
    "git": {
        "remote": "git@github.com:ZachLevine-11/lab.git",
        "commit": "e4b8fb6e56ee5cd8ba109e91bbae4f71cc8feeee"
    },
    "email": "zachary.levine@weizmann.ac.il",
    "root": "/home/zacharyl/lab",
    "host": "n116.mcl11.weizmann.ac.il",
    "username": "zacharyl",
    "executable": "/home/zacharyl/miniconda3/envs/deep_learning/bin/python",
    "cpu_count": 16,
    "cpu_count_logical": 32,
    "cpu_freq": {
        "current": 2453.12534375,
        "min": 1000.0,
        "max": 3500.0
    },
    "cpu_freq_per_core": [
        {
            "current": 2500.0,
            "min": 1000.0,
            "max": 3500.0
        },
        {
            "current": 2939.738,
            "min": 1000.0,
            "max": 3500.0
        },
        {
            "current": 2500.0,
            "min": 1000.0,
            "max": 3500.0
        },
        {
            "current": 2500.0,
            "min": 1000.0,
            "max": 3500.0
        },
        {
            "current": 2500.0,
            "min": 1000.0,
            "max": 3500.0
        },
        {
            "current": 2500.0,
            "min": 1000.0,
            "max": 3500.0
        },
        {
            "current": 2500.0,
            "min": 1000.0,
            "max": 3500.0
        },
        {
            "current": 2500.0,
            "min": 1000.0,
            "max": 3500.0
        },
        {
            "current": 2500.0,
            "min": 1000.0,
            "max": 3500.0
        },
        {
            "current": 2500.0,
            "min": 1000.0,
            "max": 3500.0
        },
        {
            "current": 2500.0,
            "min": 1000.0,
            "max": 3500.0
        },
        {
            "current": 2500.0,
            "min": 1000.0,
            "max": 3500.0
        },
        {
            "current": 2500.0,
            "min": 1000.0,
            "max": 3500.0
        },
        {
            "current": 2500.0,
            "min": 1000.0,
            "max": 3500.0
        },
        {
            "current": 2500.0,
            "min": 1000.0,
            "max": 3500.0
        },
        {
            "current": 2500.0,
            "min": 1000.0,
            "max": 3500.0
        },
        {
            "current": 2500.0,
            "min": 1000.0,
            "max": 3500.0
        },
        {
            "current": 2500.0,
            "min": 1000.0,
            "max": 3500.0
        },
        {
            "current": 2500.0,
            "min": 1000.0,
            "max": 3500.0
        },
        {
            "current": 2500.0,
            "min": 1000.0,
            "max": 3500.0
        },
        {
            "current": 2500.0,
            "min": 1000.0,
            "max": 3500.0
        },
        {
            "current": 1000.008,
            "min": 1000.0,
            "max": 3500.0
        },
        {
            "current": 2500.0,
            "min": 1000.0,
            "max": 3500.0
        },
        {
            "current": 2500.0,
            "min": 1000.0,
            "max": 3500.0
        },
        {
            "current": 2500.0,
            "min": 1000.0,
            "max": 3500.0
        },
        {
            "current": 2500.0,
            "min": 1000.0,
            "max": 3500.0
        },
        {
            "current": 2500.0,
            "min": 1000.0,
            "max": 3500.0
        },
        {
            "current": 2500.0,
            "min": 1000.0,
            "max": 3500.0
        },
        {
            "current": 2500.0,
            "min": 1000.0,
            "max": 3500.0
        },
        {
            "current": 2500.0,
            "min": 1000.0,
            "max": 3500.0
        },
        {
            "current": 2500.0,
            "min": 1000.0,
            "max": 3500.0
        },
        {
            "current": 2500.0,
            "min": 1000.0,
            "max": 3500.0
        }
    ],
    "disk": {
        "/": {
            "total": 78.1898422241211,
            "used": 11.565971374511719
        }
    },
    "gpu": "Quadro RTX 6000",
    "gpu_count": 1,
    "gpu_devices": [
        {
            "name": "Quadro RTX 6000",
            "memory_total": 25769803776
        }
    ],
    "memory": {
        "total": 188.00299453735352
    }
}
